odoo/addons/partner_tier_validation/README.rst
odoo/addons/partner_tier_validation/__init__.py
odoo/addons/partner_tier_validation/__manifest__.py
odoo/addons/partner_tier_validation/data/tier_definition.xml
odoo/addons/partner_tier_validation/i18n/es.po
odoo/addons/partner_tier_validation/i18n/fr.po
odoo/addons/partner_tier_validation/i18n/it.po
odoo/addons/partner_tier_validation/i18n/partner_tier_validation.pot
odoo/addons/partner_tier_validation/models/__init__.py
odoo/addons/partner_tier_validation/models/res_partner.py
odoo/addons/partner_tier_validation/models/tier_definition.py
odoo/addons/partner_tier_validation/readme/CONFIGURATION.rst
odoo/addons/partner_tier_validation/readme/CONTRIBUTORS.rst
odoo/addons/partner_tier_validation/readme/DESCRIPTION.rst
odoo/addons/partner_tier_validation/readme/INSTALL.rst
odoo/addons/partner_tier_validation/readme/USAGE.rst
odoo/addons/partner_tier_validation/static/description/icon.png
odoo/addons/partner_tier_validation/static/description/index.html
odoo/addons/partner_tier_validation/tests/__init__.py
odoo/addons/partner_tier_validation/tests/test_tier_validation.py
odoo/addons/partner_tier_validation/views/res_partner_view.xml
odoo14_addon_partner_tier_validation-14.0.3.0.3.dist-info/METADATA
odoo14_addon_partner_tier_validation-14.0.3.0.3.dist-info/WHEEL
odoo14_addon_partner_tier_validation-14.0.3.0.3.dist-info/top_level.txt
odoo14_addon_partner_tier_validation-14.0.3.0.3.dist-info/RECORD
