Metadata-Version: 2.1
Name: odoo14-addon-partner_tier_validation
Version: 14.0.3.0.3
Summary: Support a tier validation process for Contacts
Home-page: https://github.com/OCA/partner-contact
Author: Open Source Integrators, Odoo Community Association (OCA)
Author-email: support@odoo-community.org
License: AGPL-3
Classifier: Programming Language :: Python
Classifier: Framework :: Odoo
Classifier: Framework :: Odoo :: 14.0
Classifier: License :: OSI Approved :: GNU Affero General Public License v3
Requires-Python: >=3.6
Requires-Dist: odoo14-addon-base-tier-validation
Requires-Dist: odoo14-addon-partner-stage
Requires-Dist: odoo<14.1dev,>=14.0a
